assemblyline_service_utilities/VERSION
assemblyline_service_utilities/__init__.py
assemblyline_service_utilities/py.typed
assemblyline_service_utilities/common/__init__.py
assemblyline_service_utilities/common/command_line_utils.py
assemblyline_service_utilities/common/dynamic_service_helper.py
assemblyline_service_utilities/common/icap.py
assemblyline_service_utilities/common/keytool_parse.py
assemblyline_service_utilities/common/malformed_zip.py
assemblyline_service_utilities/common/network_helper.py
assemblyline_service_utilities/common/safelist_helper.py
assemblyline_service_utilities/common/section_reducer.py
assemblyline_service_utilities/common/sysmon_helper.py
assemblyline_service_utilities/common/tag_helper.py
assemblyline_service_utilities/common/tag_reducer.py
assemblyline_service_utilities/common/balbuzard/__init__.py
assemblyline_service_utilities/common/balbuzard/balbuzard.py
assemblyline_service_utilities/common/balbuzard/bbcrack.py
assemblyline_service_utilities/common/balbuzard/patterns.py
assemblyline_service_utilities/common/extractor/__init__.py
assemblyline_service_utilities/common/extractor/base64.py
assemblyline_service_utilities/common/extractor/decode_wrapper.py
assemblyline_service_utilities/common/extractor/iocs.py
assemblyline_service_utilities/common/extractor/pe_file.py
assemblyline_service_utilities/common/pestudio/__init__.py
assemblyline_service_utilities/common/pestudio/xml/__init__.py
assemblyline_service_utilities/common/pestudio/xml/features.xml
assemblyline_service_utilities/common/pestudio/xml/functions.xml
assemblyline_service_utilities/common/pestudio/xml/languages.xml
assemblyline_service_utilities/common/pestudio/xml/resources.xml
assemblyline_service_utilities/common/pestudio/xml/signatures.xml
assemblyline_service_utilities/common/pestudio/xml/strings.xml
assemblyline_service_utilities/testing/__init__.py
assemblyline_service_utilities/testing/helper.py
assemblyline_service_utilities/testing/regenerate_results.py
assemblyline_service_utilities-4.6.1.0.dist-info/LICENCE.md
assemblyline_service_utilities-4.6.1.0.dist-info/METADATA
assemblyline_service_utilities-4.6.1.0.dist-info/WHEEL
assemblyline_service_utilities-4.6.1.0.dist-info/top_level.txt
assemblyline_service_utilities-4.6.1.0.dist-info/RECORD
